sphinxcontrib_getthecode-1.2.1-py3.8-nspkg.pth
sphinxcontrib/getthecode.py
sphinxcontrib_getthecode-1.2.1.dist-info/LICENSE.txt
sphinxcontrib_getthecode-1.2.1.dist-info/METADATA
sphinxcontrib_getthecode-1.2.1.dist-info/WHEEL
sphinxcontrib_getthecode-1.2.1.dist-info/namespace_packages.txt
sphinxcontrib_getthecode-1.2.1.dist-info/top_level.txt
sphinxcontrib_getthecode-1.2.1.dist-info/RECORD
