Metadata-Version: 2.1
Name: sphinxcontrib-getthecode
Version: 1.2.1
Summary: Sphinx getthecode extension
Home-page: https://github.com/FabriceSalvaire/sphinx-getthecode
Author: Fabrice SALVAIRE
Author-email: fabrice.salvaire@orange.fr
Maintainer: Fabrice SALVAIRE
Maintainer-email: fabrice.salvaire@orange.fr
License: GPLv3
Download-URL: http://pypi.python.org/pypi/sphinxcontrib-getthecode
Project-URL: Documentation, https://github.com/FabriceSalvaire/sphinx-getthecode
Project-URL: Code, https://github.com/FabriceSalvaire/sphinx-getthecode
Project-URL: Issue Tracker, https://github.com/FabriceSalvaire/sphinx-getthecode/issues
Keywords: sphinx,extension,literalinclude
Platform: any
Classifier: Development Status :: 5 - Production/Stable
Classifier: Environment :: Console
Classifier: Environment :: Web Environment
Classifier: Intended Audience :: Developers
Classifier: License :: OSI Approved :: GNU General Public License v3 (GPLv3)
Classifier: Operating System :: OS Independent
Classifier: Programming Language :: Python :: 3
Classifier: Topic :: Documentation
Classifier: Topic :: Software Development :: Documentation
Classifier: Topic :: Utilities
Requires-Python: >=3
